mrjson.cpython-39-i386-linux-gnu.so
mrjson-1.4.dist-info/RECORD
mrjson-1.4.dist-info/WHEEL
mrjson-1.4.dist-info/LICENSE.txt
mrjson-1.4.dist-info/METADATA
mrjson-1.4.dist-info/top_level.txt
