Metadata-Version: 2.1
Name: mrjson
Version: 1.4
Summary: JSON encoder and decoder for Python
Home-page: https://github.com/MarkReedZ/mrjson
Download-URL: https://github.com/MarkReedZ/mrjson/archive/v1.4.tar.gz
Author: Mark Reed
Author-email: mark@untilfluent.com
License: MIT License
Keywords: json mrjson
Platform: any
Classifier: Development Status :: 5 - Production/Stable
Classifier: Intended Audience :: Developers
Classifier: License :: OSI Approved :: MIT License
Classifier: Programming Language :: C
Classifier: Programming Language :: C++
Classifier: Programming Language :: Python :: 2.6
Classifier: Programming Language :: Python :: 2.7
Classifier: Programming Language :: Python :: 3
Classifier: Programming Language :: Python
License-File: LICENSE.txt
